{
   "slug": "SchweineSystem",
   "name": "SchweineSystem",
   "version": "2.0.0",
   "license": "MIT",
   "brand": "SchweineSystem",
   "author": "Ralf Waspe",
   "authorEmail": "rwaspe@me.com",
   "authorUrl": "",
   "pluginUrl": "",
   "manualUrl": "",
   "sourceUrl": "",
   "donateUrl": "",
   "changelogUrl": "",
   "modules": [
      {
         "slug": "MetropolixClock",
         "name": "MetropolixClock",
         "description": "",
         "tags": [
            "Utility",
            "Midi",
            "Clock"
         ]
      },
      {
         "slug": "BitBusCounter",
         "name": "BitBus Counter",
         "description": "count events and create a ramp",
         "tags": [
            "Logic"
         ]
      },
      {
         "slug": "BitBusCVIn",
         "name": "BitBus CV Input",
         "description": "turn CV intp 8 bits",
         "tags": [
            "Logic",
            "Polyphonic"
         ]
      },
      {
         "slug": "BitBusBitOut",
         "name": "BitBus Bit Output",
         "description": "get 8 bits",
         "tags": [
            "Logic",
            "Polyphonic",
            "Expander"
         ]
      },
      {
         "slug": "BitBusMeterAndFreeze",
         "name": "BitBus Meter And Freeze",
         "description": "freeze all bits",
         "tags": [
            "Logic",
            "Polyphonic",
            "Expander"
         ]
      },
      {
         "slug": "BitBusNegate",
         "name": "BitBus Negate",
         "description": "Negate individual bits",
         "tags": [
            "Logic",
            "Polyphonic",
            "Expander"
         ]
      },
      {
         "slug": "BitBusBitIn",
         "name": "BitBus Bit Input",
         "description": "set 8 bits",
         "tags": [
            "Logic",
            "Polyphonic"
         ]
      },
      {
         "slug": "BitBusRandomWalk",
         "name": "BitBus Random Walk",
         "description": "replace ramp bits with random walk tables",
         "tags": [
            "Logic",
            "Polyphonic",
            "Expander"
         ]
      },
      {
         "slug": "BitBusCVOut",
         "name": "BitBus CV Output",
         "description": "turn 8 bits into CV",
         "tags": [
            "Logic",
            "Polyphonic",
            "Expander"
         ]
      },
      {
         "slug": "GateLatch",
         "name": "Gate To Latch",
         "description": "Turn gates or triggers into latches",
         "tags": [
            "Utility"
         ]
      },
      {
         "slug": "Revoicer",
         "name": "Revoicer",
         "description": "",
         "tags": [
            "Noise",
            "Effect"
         ]
      },
      {
         "slug": "WavPlayer",
         "name": "Wav Player",
         "description": "Play WAV files",
         "tags": [
            "Oscillator",
            "Polyphonic"
         ]
      },
      {
         "slug": "MidiReplay",
         "name": " MidiReplay",
         "description": "Playback Midi files",
         "tags": [
            "Midi",
            "Sequencer"
         ]
      },
      {
         "slug": "MidiCV",
         "name": "Midi CV",
         "description": "Convert midi (from Midi Replay) to CV",
         "tags": [
            "Expander",
            "Sequencer",
            "Midi",
            "Polyphonic"
         ]
      },
      {
         "slug": "DoepferQuad",
         "name": "DoepferQuad",
         "description": "Send midi (from Midi Replay) to Dopefer Quad Midi Interface",
         "tags": [
            "Midi",
            "Expander",
            "External"
         ]
      },
      {
         "slug": "AturiaStep",
         "name": "AturiaStep",
         "description": "Send midi (from Midi Replay) to Aturia Keystep Pro change program banks",
         "tags": [
            "Midi",
            "Expander",
            "External"
         ]
      },
      {
         "slug": "MeshStack",
         "name": "Mesh Stack",
         "description": "",
         "tags": [
            "Oscillator",
            "Polyphonic"
         ]
      },
      {
         "slug": "RemoteScript",
         "name": "Remote Script",
         "description": "Execute a remote python script",
         "tags": [
            "Utility"
         ]
      },
      {
         "slug": "VCMCReceiver",
         "name": "VCMCReceiver",
         "description": "Receive data from a Befaco VCMC",
         "tags": [
            "External",
            "Midi",
            "Polyphonic"
         ]
      },
      {
         "slug": "TrackerWorker",
         "name": "TrackerWorker",
         "description": "A CV tracker, companion to Tracker UI",
         "tags": [
            "Sequencer",
            "Utility"
         ]
      },
      {
         "slug": "FlameCCSender",
         "name": "FlameCCSender",
         "description": "Set voltages on Flamme CC",
         "tags": [
            "External",
            "Midi",
            "Polyphonic"
         ]
      },
      {
         "slug": "HubConnect",
         "name": "HubConnect",
         "description": "Manually connect to HubVCV",
         "tags": [
            "External",
            "Utility"
         ]
      },
      {
         "slug": "ScionExciter",
         "name": "ScionExciter",
         "description": "Artificial bio feedback signal",
         "tags": [
            "External",
            "LFO"
         ]
      },
      {
         "slug": "Multifilter",
         "name": "Multifilter",
         "description": "Pitch controlled filterbank",
         "tags": [
            "Filter",
            "Polyphonic"
         ]
      },
      {
         "slug": "Mapper",
         "name": "Mapper",
         "description": "map voltage ranges",
         "tags": [
            "Utility",
            "Polyphonic"
         ]
      },
      {
         "slug": "NosferatuVampyre",
         "name": "Nosferatu Vampyre",
         "description": "a metropolis inspired sequencer",
         "tags": [
            "Sequencer"
         ]
      },
      {
         "slug": "NosferatuAcolyte",
         "name": "Nosferatu Acolyte",
         "description": "Extend Nosferatus Influence",
         "tags": [
            "Sequencer",
            "Expander"
         ]
      }
   ]
}